videoprof/__init__.py
videoprof/__main__.py
videoprof/attribute.py
videoprof/config.py
videoprof/db.py
videoprof/default_config.json
videoprof/exceptions.py
videoprof/level.py
videoprof/mediainfo.py
videoprof/preference.py
videoprof/progress.py
videoprof/py.typed
videoprof/quality.py
videoprof/video.py
videoprof/videoprof.py
videoprof-0.3.0.dist-info/entry_points.txt
videoprof-0.3.0.dist-info/WHEEL
videoprof-0.3.0.dist-info/METADATA
videoprof-0.3.0.dist-info/RECORD
