Metadata-Version: 2.1
Name: videoprof
Version: 0.3.0
Summary: Video Profiler - profile various attributes of local videos like resolution, codec, container, audio channels, and more!
License: MIT
Keywords: videoprof,video,profile,profiler,mediainfo,resolution,codec,container,collection
Author: Christian Lent
Author-email: christian@lent.us
Requires-Python: >=3.6,<4.0
Classifier: Development Status :: 3 - Alpha
Classifier: Environment :: Console
Classifier: Intended Audience :: End Users/Desktop
Classifier: Intended Audience :: System Administrators
Classifier: License :: OSI Approved :: MIT License
Classifier: Natural Language :: English
Classifier: Operating System :: POSIX :: Linux
Classifier: Programming Language :: Python :: 3
Classifier: Programming Language :: Python :: 3.6
Classifier: Programming Language :: Python :: 3.7
Classifier: Programming Language :: Python :: 3.8
Classifier: Programming Language :: Python :: 3.9
Classifier: Topic :: Multimedia :: Video
Requires-Dist: appdirs (>=1.4.4,<2.0.0)
Requires-Dist: click (>=7.1.2,<8.0.0)
Requires-Dist: colored (>=1.4.2,<2.0.0)
Requires-Dist: dataclasses (>=0.8,<0.9); python_version < "3.7"
Requires-Dist: pymediainfo (>=5.0.3,<6.0.0)
Requires-Dist: typing-extensions (>=3.7.4,<4.0.0)
